fairdetect_group_e/__init__.py
fairdetect_group_e-0.1.dist-info/METADATA
fairdetect_group_e-0.1.dist-info/WHEEL
fairdetect_group_e-0.1.dist-info/top_level.txt
fairdetect_group_e-0.1.dist-info/RECORD
